{
	"start":	{
		"connected":	[{
				"socket":	8,
				"local_host":	"172.16.0.103",
				"local_port":	53382,
				"remote_host":	"172.17.0.103",
				"remote_port":	5201
			}],
		"version":	"iperf 3.16",
		"system_info":	"Linux h1 6.12.54-0b264c55b-l4steam-117 #1 SMP PREEMPT_DYNAMIC Fri Nov  7 18:07:57 UTC 2025 x86_64",
		"timestamp":	{
			"time":	"Sun, 22 Feb 2026 02:46:38 GMT",
			"timesecs":	1771728398
		},
		"connecting_to":	{
			"host":	"172.17.0.103",
			"port":	5201
		},
		"cookie":	"hyriyelktlrbztab5sl4t5c5ep6swefhgsai",
		"tcp_mss_default":	1448,
		"target_bitrate":	0,
		"fq_rate":	0,
		"sock_bufsize":	0,
		"sndbuf_actual":	1000000,
		"rcvbuf_actual":	1000000,
		"test_start":	{
			"protocol":	"TCP",
			"num_streams":	1,
			"blksize":	131072,
			"omit":	0,
			"duration":	0,
			"bytes":	107374182,
			"blocks":	0,
			"reverse":	0,
			"tos":	0,
			"target_bitrate":	0,
			"bidir":	0,
			"fqrate":	0
		}
	},
	"intervals":	[{
			"streams":	[{
					"socket":	8,
					"start":	0,
					"end":	1.001044,
					"seconds":	1.0010440349578857,
					"bytes":	19267584,
					"bits_per_second":	153979911.58948842,
					"retransmits":	313,
					"snd_cwnd":	101387512,
					"snd_wnd":	19456000,
					"rtt":	351650,
					"rttvar":	16661,
					"pmtu":	1500,
					"omitted":	false,
					"sender":	true
				}],
			"sum":	{
				"start":	0,
				"end":	1.001044,
				"seconds":	1.0010440349578857,
				"bytes":	19267584,
				"bits_per_second":	153979911.58948842,
				"retransmits":	313,
				"omitted":	false,
				"sender":	true
			}
		}, {
			"streams":	[{
					"socket":	8,
					"start":	1.001044,
					"end":	2.001074,
					"seconds":	1.0000300407409668,
					"bytes":	10747904,
					"bits_per_second":	85980649.0775929,
					"retransmits":	4987,
					"snd_cwnd":	70989648,
					"snd_wnd":	42704896,
					"rtt":	104745,
					"rttvar":	3720,
					"pmtu":	1500,
					"omitted":	false,
					"sender":	true
				}],
			"sum":	{
				"start":	1.001044,
				"end":	2.001074,
				"seconds":	1.0000300407409668,
				"bytes":	10747904,
				"bits_per_second":	85980649.0775929,
				"retransmits":	4987,
				"omitted":	false,
				"sender":	true
			}
		}, {
			"streams":	[{
					"socket":	8,
					"start":	2.001074,
					"end":	3.001046,
					"seconds":	0.99997198581695557,
					"bytes":	26607616,
					"bits_per_second":	212866891.29205677,
					"retransmits":	2635,
					"snd_cwnd":	3381080,
					"snd_wnd":	67190784,
					"rtt":	102929,
					"rttvar":	3868,
					"pmtu":	1500,
					"omitted":	false,
					"sender":	true
				}],
			"sum":	{
				"start":	2.001074,
				"end":	3.001046,
				"seconds":	0.99997198581695557,
				"bytes":	26607616,
				"bits_per_second":	212866891.29205677,
				"retransmits":	2635,
				"omitted":	false,
				"sender":	true
			}
		}, {
			"streams":	[{
					"socket":	8,
					"start":	3.001046,
					"end":	4.001048,
					"seconds":	1.0000020265579224,
					"bytes":	50855936,
					"bits_per_second":	406846663.5016709,
					"retransmits":	970,
					"snd_cwnd":	4810256,
					"snd_wnd":	91357184,
					"rtt":	398850,
					"rttvar":	4593,
					"pmtu":	1500,
					"omitted":	false,
					"sender":	true
				}],
			"sum":	{
				"start":	3.001046,
				"end":	4.001048,
				"seconds":	1.0000020265579224,
				"bytes":	50855936,
				"bits_per_second":	406846663.5016709,
				"retransmits":	970,
				"omitted":	false,
				"sender":	true
			}
		}],
	"end":	{
		"streams":	[{
				"sender":	{
					"socket":	8,
					"start":	0,
					"end":	4.001418,
					"seconds":	4.001418,
					"bytes":	107479040,
					"bits_per_second":	214881904.36490265,
					"retransmits":	8905,
					"max_snd_cwnd":	101387512,
					"max_snd_wnd":	91357184,
					"max_rtt":	398850,
					"min_rtt":	102929,
					"mean_rtt":	271404,
					"sender":	true
				},
				"receiver":	{
					"socket":	8,
					"start":	0,
					"end":	4.084703,
					"seconds":	4.001418,
					"bytes":	43778048,
					"bits_per_second":	85740477.09221454,
					"sender":	true
				}
			}],
		"sum_sent":	{
			"start":	0,
			"end":	4.001418,
			"seconds":	4.001418,
			"bytes":	107479040,
			"bits_per_second":	214881904.36490265,
			"retransmits":	8905,
			"sender":	true
		},
		"sum_received":	{
			"start":	0,
			"end":	4.084703,
			"seconds":	4.084703,
			"bytes":	43778048,
			"bits_per_second":	85740477.09221454,
			"sender":	true
		},
		"cpu_utilization_percent":	{
			"host_total":	7.5026452729399784,
			"host_user":	5.9874384751773864,
			"host_system":	1.5152067977625909,
			"remote_total":	1.1407895042861007,
			"remote_user":	0,
			"remote_system":	1.1408139857982749
		},
		"sender_tcp_congestion":	"cubic",
		"receiver_tcp_congestion":	"cubic"
	}
}
